databricks/__init__.py
databricks/labs/__init__.py
databricks/labs/remorph/__about__.py
databricks/labs/remorph/__init__.py
databricks/labs/remorph/cli.py
databricks/labs/remorph/config.py
databricks/labs/remorph/install.py
databricks/labs/remorph/jvmproxy.py
databricks/labs/remorph/lineage.py
databricks/labs/remorph/uninstall.py
databricks/labs/remorph/contexts/__init__.py
databricks/labs/remorph/contexts/application.py
databricks/labs/remorph/coverage/__init__.py
databricks/labs/remorph/coverage/commons.py
databricks/labs/remorph/coverage/local_report.py
databricks/labs/remorph/coverage/remorph_snow_transpilation_coverage.py
databricks/labs/remorph/coverage/sqlglot_snow_transpilation_coverage.py
databricks/labs/remorph/coverage/sqlglot_tsql_transpilation_coverage.py
databricks/labs/remorph/deployment/__init__.py
databricks/labs/remorph/deployment/configurator.py
databricks/labs/remorph/deployment/dashboard.py
databricks/labs/remorph/deployment/installation.py
databricks/labs/remorph/deployment/job.py
databricks/labs/remorph/deployment/recon.py
databricks/labs/remorph/deployment/table.py
databricks/labs/remorph/deployment/upgrade_common.py
databricks/labs/remorph/helpers/__init__.py
databricks/labs/remorph/helpers/db_sql.py
databricks/labs/remorph/helpers/execution_time.py
databricks/labs/remorph/helpers/file_utils.py
databricks/labs/remorph/helpers/metastore.py
databricks/labs/remorph/helpers/morph_status.py
databricks/labs/remorph/helpers/recon_config_utils.py
databricks/labs/remorph/helpers/validation.py
databricks/labs/remorph/intermediate/__init__.py
databricks/labs/remorph/intermediate/dag.py
databricks/labs/remorph/intermediate/engine_adapter.py
databricks/labs/remorph/intermediate/root_tables.py
databricks/labs/remorph/reconcile/__init__.py
databricks/labs/remorph/reconcile/compare.py
databricks/labs/remorph/reconcile/constants.py
databricks/labs/remorph/reconcile/exception.py
databricks/labs/remorph/reconcile/execute.py
databricks_labs_remorph-0.9.1.dist-info/METADATA
databricks_labs_remorph-0.9.1.dist-info/WHEEL
databricks_labs_remorph-0.9.1.dist-info/entry_points.txt
databricks_labs_remorph-0.9.1.dist-info/licenses/LICENSE
databricks_labs_remorph-0.9.1.dist-info/licenses/NOTICE
databricks_labs_remorph-0.9.1.dist-info/RECORD
